pipekit/__init__.py
pipekit/component.py
pipekit/engine.py
pipekit/filter.py
pipekit/message.py
pipekit/node.py
pipekit/pipe.py
pipekit/utils.py
pipekit/workflow.py
pipekit-0.3.5.dist-info/LICENSE
pipekit-0.3.5.dist-info/METADATA
pipekit-0.3.5.dist-info/WHEEL
pipekit-0.3.5.dist-info/entry_points.txt
pipekit-0.3.5.dist-info/top_level.txt
pipekit-0.3.5.dist-info/RECORD
