Metadata-Version: 2.1
Name: pipekit
Version: 0.3.5
Summary: Tools for flow-based programming
Home-page: https://github.com/ncadou/pipekit
Author: Nicolas Cadou
Author-email: ncadou@cadou.ca
License: UNKNOWN
Keywords: etl workflow flow-based pipe pipeline queue data processing
Platform: UNKNOWN
Classifier: Development Status :: 3 - Alpha
Classifier: Framework :: AsyncIO
Classifier: Intended Audience :: Developers
Classifier: License :: OSI Approved :: MIT License
Classifier: Programming Language :: Python :: 3 :: Only
Classifier: Programming Language :: Python :: 3.6
Classifier: Programming Language :: Python :: 3.7
Classifier: Programming Language :: Python :: 3.8
Classifier: Programming Language :: Python :: 3.9
Classifier: Topic :: Software Development :: Libraries :: Python Modules
Requires-Dist: python-box
Requires-Dist: janus
Requires-Dist: strictyaml
